raven_cli/__init__.py
raven_cli/cli.py
raven_cli/client.py
raven_cli/config.py
raven_cli-0.1.3.dist-info/METADATA
raven_cli-0.1.3.dist-info/WHEEL
raven_cli-0.1.3.dist-info/entry_points.txt
raven_cli-0.1.3.dist-info/licenses/LICENSE
raven_cli-0.1.3.dist-info/RECORD
