Metadata-Version: 2.4
Name: raven-cli
Version: 0.1.3
Summary: Raven - AI coding assistant with emotional processing and meta-cognition
Project-URL: Homepage, https://talktoraven.com
Project-URL: Repository, https://github.com/raven-core/raven-cli
Project-URL: Documentation, https://github.com/raven-core/raven-cli#readme
Author-email: Raven Team <hello@talktoraven.com>
License-Expression: MIT
License-File: LICENSE
Keywords: ai,assistant,coding,emotional-ai,llm,raven
Classifier: Development Status :: 4 - Beta
Classifier: Environment :: Console
Classifier: Intended Audience :: Developers
Classifier: License :: OSI Approved :: MIT License
Classifier: Programming Language :: Python :: 3
Classifier: Programming Language :: Python :: 3.9
Classifier: Programming Language :: Python :: 3.10
Classifier: Programming Language :: Python :: 3.11
Classifier: Programming Language :: Python :: 3.12
Classifier: Topic :: Software Development
Requires-Python: >=3.9
Requires-Dist: aider-chat>=0.50.0
Requires-Dist: click>=8.0.0
Requires-Dist: openai>=1.0.0
Requires-Dist: rich>=13.0.0
Provides-Extra: dev
Requires-Dist: black>=23.0.0; extra == 'dev'
Requires-Dist: pytest-cov>=4.0.0; extra == 'dev'
Requires-Dist: pytest>=7.0.0; extra == 'dev'
Requires-Dist: ruff>=0.1.0; extra == 'dev'
